webpage2content/VERSION
webpage2content/__init__.py
webpage2content/webpage2content_impl.py
webpage2content-1.3.4.dist-info/LICENSE
webpage2content-1.3.4.dist-info/METADATA
webpage2content-1.3.4.dist-info/WHEEL
webpage2content-1.3.4.dist-info/entry_points.txt
webpage2content-1.3.4.dist-info/top_level.txt
webpage2content-1.3.4.dist-info/RECORD
