Metadata-Version: 2.1
Name: webpage2content
Version: 1.3.4
Summary: A simple Python package to extract text content from a webpage.
Home-page: https://github.com/Mighty-Data-Inc/webpage2content
Author: Mikhail Voloshin
Author-email: mvol@mightydatainc.com
License: Apache-2.0
Platform: UNKNOWN
Classifier: Programming Language :: Python :: 3
Classifier: License :: OSI Approved :: Apache Software License
Classifier: Operating System :: OS Independent
Requires-Python: >=3.9
License-File: LICENSE
Requires-Dist: beautifulsoup4
Requires-Dist: html2text
Requires-Dist: openai
Requires-Dist: python-dotenv
Requires-Dist: requests
